<?xml version="1.0" encoding="utf-8"?>
<base xmlns:xsi="http://www.w3.org/2001/XMLSchema-instance" xmlns:xsd="http://www.w3.org/2001/XMLSchema" type="string">
  <tags>
    <tag language="Türkçe" />
  </tags>
  <strings>
    <string id="8eYtra7T" text="Выберите сложность игры" />
    <string id="fz2kQjFS" text="Выберите культуру вашего персонажа:" />
    <string id="K6GYskvJ" text="Культура:" />
    <string id="kek1czyb" text="Вместе с вашим братом вы готовитесь ступить на путь мести и спасения. Вот ваш персонаж. Продолжите, если вы готовы, или вернитесь назад для внесения изменений." />
    <string id="MaHMOzL2" text="Культура персонажа" />
    <string id="mHVmrwRQ" text="Введите имя персонажа" />
    <string id="PUjDWe5j" text="Культура" />
    <string id="raD9MK3O" text="Сложность" />
    <string id="txjiykNa" text="Обзор" />
  </strings>
</base>